Metadata-Version: 2.1
Name: odoo-addon-endpoint_route_handler
Version: 18.0.1.1.0.2
Requires-Python: >=3.10
Requires-Dist: odoo==18.0.*
Summary: Provide mixin and tool to generate custom endpoints on the fly.
Home-page: https://github.com/OCA/web-api
License: LGPL-3
Author: Camptocamp,Odoo Community Association (OCA)
Author-email: support@odoo-community.org
Classifier: Programming Language :: Python
Classifier: Framework :: Odoo
Classifier: Framework :: Odoo :: 18.0
Classifier: License :: OSI Approved :: GNU Lesser General Public License v3 (LGPLv3)
Classifier: Development Status :: 4 - Beta
